fractals/__init__.py
fractals/fractals.py
fractals/main.py
fractals-0.0.3.dist-info/LICENSE
fractals-0.0.3.dist-info/METADATA
fractals-0.0.3.dist-info/WHEEL
fractals-0.0.3.dist-info/top_level.txt
fractals-0.0.3.dist-info/RECORD
