Metadata-Version: 2.1
Name: fractals
Version: 0.0.3
Summary: A simple fractal generator
Home-page: https://github.com/Fomys/Fractals
Author: Fomys
Author-email: fomys@gmx.us
License: UNKNOWN
Platform: UNKNOWN
Classifier: Programming Language :: Python :: 3
Classifier: License :: OSI Approved :: MIT License
Classifier: Operating System :: OS Independent
